{
	"pages": [ //pages数组中第一项表示应用启动页，参考：https://uniapp.dcloud.io/collocation/pages
		{
			"path": "pages/index/index",
			"style": {
				"navigationBarTitleText": "这里的权重更高，页面更高"		// 此处比globalStyle.navigationBarTitleText权重更大
			}
		},
		{
			"path" : "pages/classify/classify",
			"style" : 
			{
				"enablePullDownRefresh" : false
			}
		}
	],
	"globalStyle": {
		"navigationBarTextStyle": "white",
		"navigationBarTitleText": "page.json页面说明",
		"navigationBarBackgroundColor": "#2B9939",
		"backgroundColor": "#F8F8F8",		// 只支持微信小程序
		"enablePullDownRefresh": true,
		
		// "navigationStyle": "custom"  // custom 自定义导航栏，会导致上述设置均失效
		"onReachBottomDistance": 250
	},
	"uniIdRouter": {}
}
